fenics_plotly/__init__.py
fenics_plotly/fenics_plotly.py
fenics_plotly-2025.0.0.dist-info/licenses/LICENSE
fenics_plotly-2025.0.0.dist-info/METADATA
fenics_plotly-2025.0.0.dist-info/WHEEL
fenics_plotly-2025.0.0.dist-info/top_level.txt
fenics_plotly-2025.0.0.dist-info/RECORD
